{
  "date": "2026-04-22",
  "poem": {
    "content": "The desert stretches, where useless dreams\nAcquire a phantom weight, like beefy limbs\nOf ancient cactus, tasting ash and spite.\n\nA general's ghost wanders in the light,\nAlso seeking what he could not bring--\nA gentler fate, before the vultures sing.\n\nThe battlefield, a split in time's own face,\nReveals the rose, in this forsaken space.\nNo silk to ease the pain, no solace found,\nJust lion's roar upon the barren ground.\n\nThe taste of loss, a bitter draught to hold,\nA story whispered, never to grow old.\nHe sought to bring a solace, pure and deep,\nBut found only silence, where secrets sleep.\n\nIf I could split the sky, and show you then,\nThe useless burden carried by all men,\nThe cactus blooms, in space so very wide,\nA desert bloom, where silent wishes hide.",
    "generatedAt": "2026-04-22T10:07:19.879Z"
  },
  "keywords": [
    {
      "word": "cactus",
      "slot": 414888705,
      "source": "blockhash"
    },
    {
      "word": "taste",
      "slot": 414888705,
      "source": "previousBlockhash"
    },
    {
      "word": "acquire",
      "slot": 414888705,
      "source": "transaction"
    },
    {
      "word": "split",
      "slot": 414870705,
      "source": "blockhash"
    },
    {
      "word": "useless",
      "slot": 414870705,
      "source": "previousBlockhash"
    },
    {
      "word": "beef",
      "slot": 414870705,
      "source": "transaction"
    },
    {
      "word": "lion",
      "slot": 414852705,
      "source": "blockhash"
    },
    {
      "word": "bring",
      "slot": 414852705,
      "source": "previousBlockhash"
    },
    {
      "word": "also",
      "slot": 414852705,
      "source": "transaction"
    },
    {
      "word": "where",
      "slot": 414834705,
      "source": "blockhash"
    },
    {
      "word": "rose",
      "slot": 414834705,
      "source": "previousBlockhash"
    },
    {
      "word": "general",
      "slot": 414834705,
      "source": "transaction"
    },
    {
      "word": "space",
      "slot": 414816705,
      "source": "blockhash"
    },
    {
      "word": "limb",
      "slot": 414816705,
      "source": "previousBlockhash"
    },
    {
      "word": "silk",
      "slot": 414816705,
      "source": "transaction"
    }
  ],
  "blueskyUri": "at://did:plc:mthilq5pqykwxgxgvy5ixnnp/app.bsky.feed.post/3mk3atasp7v2b",
  "poemReady": true,
  "keywordsCollected": 15,
  "keywordsNeeded": 8
}