{
  "date": "2026-04-30",
  "poem": {
    "content": "The solar wind whips, a frozen kiss,\nUpon the chrome, a neon race begins.\nYouth spills out, a lottery of dreams,\nWhere fortunes rise and fall in laser beams.\n\nWe pave the way with digital despair,\nOur lives a clip, suspended in thin air.\nFury simmers, a silent, slow burn,\nWhile monitors flicker, lessons unlearned.\n\nEach dawn a prison, defined by the screen,\nGenre-bending boredom, a world unseen.\nThe ozone cracks, a warning from above,\nWhile we waste our hours on fleeting love.\n\nLong hair streams back, against the digital tide,\nA single soul where hope and fury hide.\nCan we begin again, escape the waste?\nBefore our future is forever erased.\nToo late, the clip ends, the light is gone.\nThe race is over, and the future’s pawn.",
    "generatedAt": "2026-04-30T10:31:01.642Z"
  },
  "keywords": [
    {
      "word": "pave",
      "slot": 416639028,
      "source": "blockhash"
    },
    {
      "word": "youth",
      "slot": 416639028,
      "source": "previousBlockhash"
    },
    {
      "word": "fury",
      "slot": 416639028,
      "source": "transaction"
    },
    {
      "word": "lottery",
      "slot": 416621028,
      "source": "blockhash"
    },
    {
      "word": "clip",
      "slot": 416621028,
      "source": "previousBlockhash"
    },
    {
      "word": "frozen",
      "slot": 416621028,
      "source": "transaction"
    },
    {
      "word": "race",
      "slot": 416603028,
      "source": "blockhash"
    },
    {
      "word": "waste",
      "slot": 416603028,
      "source": "previousBlockhash"
    },
    {
      "word": "begin",
      "slot": 416603028,
      "source": "transaction"
    },
    {
      "word": "ozone",
      "slot": 416585028,
      "source": "blockhash"
    },
    {
      "word": "solar",
      "slot": 416585028,
      "source": "previousBlockhash"
    },
    {
      "word": "hair",
      "slot": 416585028,
      "source": "transaction"
    },
    {
      "word": "monitor",
      "slot": 416567028,
      "source": "blockhash"
    },
    {
      "word": "genre",
      "slot": 416567028,
      "source": "previousBlockhash"
    },
    {
      "word": "prison",
      "slot": 416567028,
      "source": "transaction"
    }
  ],
  "blueskyUri": "at://did:plc:mthilq5pqykwxgxgvy5ixnnp/app.bsky.feed.post/3mkpfuyflc42k",
  "poemReady": true,
  "keywordsCollected": 15,
  "keywordsNeeded": 8
}