{
  "date": "2026-07-16",
  "poem": {
    "content": "In the vacuum of cyberspace, a world aglow,\nWhere code and wonder entwine, as electrons flake and flow,\nA blade of light cuts through the digital haze,\nExhausting doubts, as fears and hopes amaze.\n\nIn this mobile realm, where transactions take flight,\nA ripple spreads, a symphony of light,\nArctic winds of progress blow, icy and cold,\nAs life bursts forth, young and bold.\n\nBut amidst the beauty, a cage constrains the soul,\nA sense of awkward loss, a heart's crusty role,\nA shiver runs, as fragile dreams unfold,\nLike petals of a flower, in winter's cold hold.\n\nIn this virtual landscape, where hearts reside,\nA sort of order keeps, the chaos inside,\nA stillness deep, where love and fear entwine,\nA place to breathe, where spirit and soul align.\n\nYet, in the silence, a subtle hue appears,\nA color creeping, born from hidden tears,\nA beacon calling, a distant, gentle light,\nA promise kept, of a better, equable night.\n\nThe world's vast expanse, in shades of light and dark,\nA mysterious ease, within this code we embark,\nThe blade of change, slicing through the air,\nA cipher's secret, hidden beyond compare.\n\nThe vacuum pulls, as paths unfold and blend,\nA story told, where wonder never ends.",
    "generatedAt": "2026-07-16T10:46:32.634Z"
  },
  "keywords": [
    {
      "word": "quick",
      "slot": 433257737,
      "source": "blockhash"
    },
    {
      "word": "wonder",
      "slot": 433257737,
      "source": "previousBlockhash"
    },
    {
      "word": "blade",
      "slot": 433257737,
      "source": "transaction"
    },
    {
      "word": "vacuum",
      "slot": 433239737,
      "source": "blockhash"
    },
    {
      "word": "code",
      "slot": 433239737,
      "source": "previousBlockhash"
    },
    {
      "word": "life",
      "slot": 433239737,
      "source": "transaction"
    },
    {
      "word": "mobile",
      "slot": 433221737,
      "source": "blockhash"
    },
    {
      "word": "ripple",
      "slot": 433221737,
      "source": "previousBlockhash"
    },
    {
      "word": "color",
      "slot": 433221737,
      "source": "transaction"
    },
    {
      "word": "slide",
      "slot": 433203737,
      "source": "blockhash"
    },
    {
      "word": "cage",
      "slot": 433203737,
      "source": "previousBlockhash"
    },
    {
      "word": "exhaust",
      "slot": 433203737,
      "source": "transaction"
    },
    {
      "word": "shiver",
      "slot": 433185737,
      "source": "blockhash"
    },
    {
      "word": "arctic",
      "slot": 433185737,
      "source": "previousBlockhash"
    },
    {
      "word": "awkward",
      "slot": 433185737,
      "source": "transaction"
    },
    {
      "word": "sort",
      "slot": 433167737,
      "source": "blockhash"
    }
  ],
  "blueskyUri": "at://did:plc:mthilq5pqykwxgxgvy5ixnnp/app.bsky.feed.post/3mqr2nloeki2u",
  "poemReady": true,
  "keywordsCollected": 16,
  "keywordsNeeded": 8
}